[
    {
        "content": "<p>From: Jeremy Dawson &lt;<a href=\"mailto:Jeremy.Dawson@anu.edu.au\">Jeremy.Dawson@anu.edu.au</a>&gt;<br>\nConversely, if you have a term (or theorem or text string, etc) as an ML <br>\nvalue, how to you set it as the new goal (as in, eg, the lemma Isar <br>\ncommand)?</p>\n<p>Thanks</p>\n<p>Jeremy</p>",
        "id": 294735710,
        "sender_full_name": "Email Gateway",
        "timestamp": 1661189710
    },
    {
        "content": "<p>From: <a href=\"mailto:Thomas.Sewell@data61.csiro.au\">Thomas.Sewell@data61.csiro.au</a><br>\nI have an incantation for taking a thm and making it the goal. You can <br>\nalso turn props into trivial thms, for instance:</p>\n<p>ML {* val thm = Thm.trivial @{cprop \"Suc 0 = 1\"} *}</p>\n<p>schematic_goal \"PROP ?P\"<br>\n   apply (tactic {* resolve_tac @{context} [thm] 1 *})<br>\n   apply ...</p>\n<p>Cheers,<br>\n     Thomas.</p>",
        "id": 294735727,
        "sender_full_name": "Email Gateway",
        "timestamp": 1661189719
    },
    {
        "content": "<p>From: Manuel Eberl &lt;<a href=\"mailto:eberlm@in.tum.de\">eberlm@in.tum.de</a>&gt;<br>\nThere is this thread from a few years ago:<br>\n<a href=\"https://lists.cam.ac.uk/pipermail/cl-isabelle-users/2015-June/msg00076.html\">https://lists.cam.ac.uk/pipermail/cl-isabelle-users/2015-June/msg00076.html</a></p>\n<p>Cheers,</p>\n<p>Manuel</p>",
        "id": 294735733,
        "sender_full_name": "Email Gateway",
        "timestamp": 1661189722
    },
    {
        "content": "<p>From: Jeremy Dawson &lt;<a href=\"mailto:Jeremy.Dawson@anu.edu.au\">Jeremy.Dawson@anu.edu.au</a>&gt;<br>\nHi Thomas,</p>\n<p>Thanks very much - very clever!  And most useful.</p>\n<p>Cheers,</p>\n<p>Jeremy</p>",
        "id": 294735746,
        "sender_full_name": "Email Gateway",
        "timestamp": 1661189727
    }
]