[
    {
        "content": "<p>From: Randy Pollack &lt;<a href=\"mailto:rpollack@inf.ed.ac.uk\">rpollack@inf.ed.ac.uk</a>&gt;<br>\nIs there an example in the HOL sources of defining a function from a  <br>\nsingle valued relation.  I want to specify the equations of the  <br>\nfunction as simp rules, and also be able to go back and forth from  <br>\nrelational statements to equivalent functional statements.</p>\n<p>Thanks for any pointers that could save me time figuring out how to do this.</p>\n<p>Randy</p>",
        "id": 294082226,
        "sender_full_name": "Email Gateway",
        "timestamp": 1660831054
    },
    {
        "content": "<p>From: Lawrence Paulson &lt;<a href=\"mailto:lp15@cam.ac.uk\">lp15@cam.ac.uk</a>&gt;<br>\nYou could look at the definition of the finite set fold functional in  <br>\nthe file Finite_Set.thy. There is also an associated paper: <a href=\"http://www.cl.cam.ac.uk/~lp15/papers/Reports/TPHOLs05.pdf\">http://www.cl.cam.ac.uk/~lp15/papers/Reports/TPHOLs05.pdf</a><br>\nLarry</p>",
        "id": 294082229,
        "sender_full_name": "Email Gateway",
        "timestamp": 1660831056
    }
]