[
    {
        "content": "<p>From: Kawin Worrasangasilpa &lt;<a href=\"mailto:kw448@cam.ac.uk\">kw448@cam.ac.uk</a>&gt;<br>\nHi,</p>\n<p>I am proving results in Isabelle/HOL in which they need the use<br>\nof Supermartingale and Azuma–Hoeffding inequality. I have been trying to<br>\nsearch for existing theorems containing them or ways to formalise them but,<br>\nunfortunately, have not yet found any. If there anyone who knows where I<br>\nshould start or an ongoing/published (or unpublished) work regarding these<br>\ntwo, if it is the case, please help me.</p>\n<p>Thanks,<br>\nKawin</p>",
        "id": 294743456,
        "sender_full_name": "Email Gateway",
        "timestamp": 1661192470
    },
    {
        "content": "<p>From: Johannes Hölzl &lt;<a href=\"mailto:johannes.hoelzl@gmx.de\">johannes.hoelzl@gmx.de</a>&gt;<br>\nDear Kawin,</p>\n<p>there is not yet much theory on Martingales. There is the definition<br>\nand some theorems (closure under addition) in AFP-DiscretePricing, but<br>\nnothing about super-martingales. Unfortunately, we even have two<br>\ntheories of filtrations:</p>\n<ul>\n<li>Filtration.thy in AFP-DiscretePricing</li>\n<li>Stopping_Time.thy in HOL-Probability</li>\n</ul>\n<p>I'm not aware of any work on these inequalities.</p>\n<p>Best,<br>\n  Johannes</p>",
        "id": 294743498,
        "sender_full_name": "Email Gateway",
        "timestamp": 1661192489
    }
]