[
    {
        "content": "<p>From: Jens Doll &lt;<a href=\"mailto:jd@cococo.de\">jd@cococo.de</a>&gt;<br>\nI am having a problem with the installation instructions. I downloaded the <br>\ncygwin Complex_Main and save it to the /usr/local. Then it was tarred with <br>\ntar -xzf HOL-*gz. Now Isabelle still says:</p>\n<p>*** Could not find theory file \"Complex_Main.thy\" in \".\", \"/home/Jens\", <br>\n\"$ISABELLE_HOME/src/HOL/Library\"<br>\n*** Theory loader: the error(s) above occurred while examining theory <br>\n\"Complex_Main\"<br>\n*** At command \"theory\".</p>\n<p>What could be wrong?</p>\n<p>Jens</p>",
        "id": 294074954,
        "sender_full_name": "Email Gateway",
        "timestamp": 1660828493
    },
    {
        "content": "<p>From: Makarius &lt;<a href=\"mailto:makarius@sketis.net\">makarius@sketis.net</a>&gt;<br>\nBy \"Isabelle\" you probably mean your Proof General session.  Here you need <br>\nto say that you want to use the \"HOL-Complex\" logic instead of the default <br>\none \"HOL\".</p>\n<p>Makarius</p>",
        "id": 294074997,
        "sender_full_name": "Email Gateway",
        "timestamp": 1660828511
    }
]