[
    {
        "content": "<p>From: John Munroe &lt;<a href=\"mailto:munddr@gmail.com\">munddr@gmail.com</a>&gt;<br>\nHi all,</p>\n<p>AFAIK, Isabelle's lambda calculus is simply typed, because the types<br>\nare built up from base types by means of =&gt;. However, there are<br>\nproduct types in HOL, so how are they encoded?</p>\n<p>Thanks for your time.</p>\n<p>John</p>",
        "id": 294221294,
        "sender_full_name": "Email Gateway",
        "timestamp": 1660897633
    },
    {
        "content": "<p>From: Lawrence Paulson &lt;<a href=\"mailto:lp15@cam.ac.uk\">lp15@cam.ac.uk</a>&gt;<br>\nOrdered pairs are represented by functions.</p>\n<p>The pair (a,b) is represented by the function \"(\\&lt;lambda&gt;x y. x = a \\&lt;and&gt; y = b)\".</p>\n<p>Details in the file HOL/Product_Type.thy.</p>\n<p>Larry Paulson</p>",
        "id": 294224095,
        "sender_full_name": "Email Gateway",
        "timestamp": 1660899060
    }
]