[
    {
        "content": "<p>From: \"Eugene W. Stark\" &lt;<a href=\"mailto:isabelle-users@starkeffect.com\">isabelle-users@starkeffect.com</a>&gt;<br>\nThis might not be new to Isabelle2019-RC2, but I thought that I had set a limit<br>\non the size of the ML heap, but it is still exceeding that and sending my system<br>\ninto thrashing mode.</p>\n<p>Contents of my ~/.isabelle/Isabelle2019-RC2/etc/settings</p>\n<p>ISABELLE_PLATFORM=\"${ISABELLE_PLATFORM64:-$ISABELLE_PLATFORM}\"<br>\nML_PLATFORM=\"${ISABELLE_PLATFORM}\"<br>\nML_HOME=\"${POLYML_HOME}/x86_64-linux\"<br>\nML_OPTIONS=\"--maxheap 12000\"</p>\n<p>ps output showing poly with --maxheap option applied:</p>\n<p>gene     18897 75.2 71.7 23475004 17680688 ?   Ssl  May21 2365:39<br>\n/opt/Isabelle2019-RC2/contrib/polyml-5.8/x86_64-linux/poly -q --maxheap 12000 --gcthreads 0 --eval<br>\n(PolyML.SaveState.loadHierarchy [\"/home/gene/.isabelle/Isabelle2019-RC2/heaps/polyml-5.8_x86_64-linux/Pure\",<br>\n\"/home/gene/.isabelle/Isabelle2019-RC2/heaps/polyml-5.8_x86_64-linux/HOL\",<br>\n\"/home/gene/.isabelle/Isabelle2019-RC2/heaps/polyml-5.8_x86_64-linux/HOL-Library\",<br>\n\"/home/gene/.isabelle/Isabelle2019-RC2/heaps/polyml-5.8_x86_64-linux/Category3\",<br>\n\"/home/gene/.isabelle/Isabelle2019-RC2/heaps/polyml-5.8_x86_64-linux/MonoidalCategory\"]; PolyML.print_depth 0) handle<br>\nexn =&gt; (TextIO.output (TextIO.stdErr, General.exnMessage exn ^ \": MonoidalCategory\\n\"); OS.Process.exit<br>\nOS.Process.failure) --eval Options.load_default () --eval Isabelle_Process.init ()</p>\n<p>Output from \"top\":</p>\n<p>PID USER      PR  NI    VIRT    RES    SHR S  %CPU %MEM     TIME+ COMMAND</p>\n<p>18897 gene      20   0 22.372g 0.016t   6104 S 127.9 71.6   2367:46 poly</p>\n<p>% uname -a<br>\nLinux <a href=\"http://home.starkeffect.com\">home.starkeffect.com</a> 4.4.0-142-generic #168-Ubuntu SMP Wed Jan 16 21:00:45 UTC 2019 x86_64 x86_64 x86_64 GNU/Linux</p>\n<p>Did I not read and follow the proper documentation?</p>",
        "id": 294755658,
        "sender_full_name": "Email Gateway",
        "timestamp": 1661197354
    }
]