[
    {
        "content": "<p>Hello everyone, I'll be in Reykjavík for ITP from 25/09 to 05/10, i.e. I have some free days before and after. No concrete plans yet, but I'm always up for hiking and climbing. If anyone else wants to do something together there, I suggest we use this thread to make plans.</p>",
        "id": 535509405,
        "sender_full_name": "Manuel Eberl",
        "timestamp": 1755784344
    },
    {
        "content": "<p>I know it's probably too late, but I will be there too. Did you find anyone that is going to? </p>\n<p>My loose plan was to go to <a href=\"https://thecave.is/\">https://thecave.is/</a> and the stuff around it on Thursday if the weather allows it.</p>",
        "id": 538089740,
        "sender_full_name": "Mathias Fleury",
        "timestamp": 1757261680
    },
    {
        "content": "<p>I'm staying at the cityhub; don't know about Peter. We don't have any concrete plans yet. Probably some hiking. Maybe climbing, but probably not since it's hard to bring gear on a flight.</p>",
        "id": 538090274,
        "sender_full_name": "Manuel Eberl",
        "timestamp": 1757262109
    },
    {
        "content": "<p>I will be there from 27/09 to 06/10, and I would be interested in the cave as well</p>",
        "id": 538172807,
        "sender_full_name": "Jan van Brügge",
        "timestamp": 1757323154
    },
    {
        "content": "<p>Ah, sorry I should have specified: I am there the week before ITP, not the week after.</p>",
        "id": 538221470,
        "sender_full_name": "Mathias Fleury",
        "timestamp": 1757336842
    }
]