[
    {
        "content": "<p>Dear Zulip users,</p>\n<p>When trying to build a GitHub project I get the following error message in the logs of the automated build job:</p>\n<div class=\"codehilite\" data-code-language=\"Isabelle\"><pre><span></span><code><span class=\"n\">***</span><span class=\"w\"> </span><span class=\"n\">Solver</span><span class=\"w\"> </span><span class=\"n\">z3</span><span class=\"o\">:</span><span class=\"w\"> </span><span class=\"n\">Solver</span><span class=\"w\"> </span><span class=\"n\">terminated</span><span class=\"w\"> </span><span class=\"n\">abnormally</span><span class=\"w\"> </span><span class=\"k\">with</span><span class=\"w\"> </span><span class=\"n\">error</span><span class=\"w\"> </span><span class=\"n\">code</span><span class=\"w\"> </span><span class=\"n\">127</span>\n<span class=\"n\">***</span><span class=\"w\"> </span><span class=\"n\">At</span><span class=\"w\"> </span><span class=\"n\">command</span><span class=\"w\"> </span><span class=\"s\">\"by\"</span><span class=\"w\"> </span><span class=\"o\">(</span><span class=\"n\">line</span><span class=\"w\"> </span><span class=\"n\">692</span><span class=\"w\"> </span><span class=\"n\">of</span><span class=\"w\"> </span><span class=\"s\">\"/opt/afp-sessions/Finite-Map-Extras/Finite_Map_Extras.thy\"</span><span class=\"o\">)</span>\n</code></pre></div>\n<p>As pointed out in the logs, the problem occurs in a call to the <code>smt</code> proof method. However, I can correctly build my project locally using the same Isabelle version (namely, Isabelle2022). Any help with this issue will be very appreciated.</p>",
        "id": 370171601,
        "sender_full_name": "Javier Diaz",
        "timestamp": 1687891566
    },
    {
        "content": "<p>To clarify: This happens when trying to build the session within GitHub Actions.</p>",
        "id": 370454583,
        "sender_full_name": "Wolfgang Jeltsch",
        "timestamp": 1687962860
    }
]